{"Venser, the Sojourner":{"cmc":5,"colors":"WU","rarity":"M"},"Whitemane Lion":{"cmc":2,"colors":"W","rarity":"C"},"Augury Owl":{"cmc":2,"colors":"U","rarity":"C"},"Coral Fighters":{"cmc":2,"colors":"U","rarity":"U"},"Minamo Sightbender":{"cmc":2,"colors":"U","rarity":"U"},"Mistmeadow Witch":{"cmc":2,"colors":"WU","rarity":"U"},"Scroll Thief":{"cmc":3,"colors":"U","rarity":"C"},"Neurok Invisimancer":{"cmc":3,"colors":"U","rarity":"C"},"Slith Strider":{"cmc":3,"colors":"U","rarity":"U"},"Sky Spirit":{"cmc":3,"colors":"WU","rarity":"U"},"Wall of Denial":{"cmc":3,"colors":"WU","rarity":"U"},"Galepowder Mage":{"cmc":4,"colors":"W","rarity":"R"},"Kor Cartographer":{"cmc":4,"colors":"W","rarity":"C"},"Clone":{"cmc":4,"colors":"U","rarity":"R"},"Cryptic Annelid":{"cmc":4,"colors":"U","rarity":"U"},"Primal Plasma":{"cmc":4,"colors":"U","rarity":"C"},"Sawtooth Loon":{"cmc":4,"colors":"WU","rarity":"U"},"Cache Raiders":{"cmc":5,"colors":"U","rarity":"U"},"Windreaver":{"cmc":5,"colors":"WU","rarity":"R"},"Jedit's Dragoons":{"cmc":6,"colors":"W","rarity":"C"},"Sunblast Angel":{"cmc":6,"colors":"W","rarity":"R"},"Sphinx of Uthuun":{"cmc":7,"colors":"U","rarity":"R"},"Path to Exile":{"cmc":1,"colors":"W","rarity":"U"},"Preordain":{"cmc":1,"colors":"U","rarity":"C"},"Sigil of Sleep":{"cmc":1,"colors":"U","rarity":"C"},"Revoke Existence":{"cmc":2,"colors":"W","rarity":"C"},"Angelic Shield":{"cmc":2,"colors":"WU","rarity":"U"},"Oblivion Ring":{"cmc":3,"colors":"W","rarity":"U"},"Safe Passage":{"cmc":3,"colors":"W","rarity":"C"},"Steel of the Godhead":{"cmc":3,"colors":"WU","rarity":"C"},"Vanish into Memory":{"cmc":4,"colors":"WU","rarity":"U"},"Overrule":{"cmc":2,"colors":"WU","rarity":"C"},"Azorius Chancery":{"cmc":0,"colors":"WU","rarity":"C"},"Flood Plain":{"cmc":0,"colors":"C","rarity":"U"},"New Benalia":{"cmc":0,"colors":"W","rarity":"U"},"Sejiri Refuge":{"cmc":0,"colors":"WU","rarity":"U"},"Soaring Seacliff":{"cmc":0,"colors":"U","rarity":"C"},"Plains":{"cmc":0,"colors":"W","rarity":"B"},"Island":{"cmc":0,"colors":"U","rarity":"B"},"Koth of the Hammer":{"cmc":4,"colors":"R","rarity":"M"},"Plated Geopede":{"cmc":2,"colors":"R","rarity":"C"},"Pygmy Pyrosaur":{"cmc":2,"colors":"R","rarity":"C"},"Pilgrim's Eye":{"cmc":3,"colors":"C","rarity":"C"},"Æther Membrane":{"cmc":3,"colors":"R","rarity":"U"},"Fiery Hellhound":{"cmc":3,"colors":"R","rarity":"C"},"Vulshok Sorcerer":{"cmc":3,"colors":"R","rarity":"C"},"Anger":{"cmc":4,"colors":"R","rarity":"U"},"Cosi's Ravager":{"cmc":4,"colors":"R","rarity":"C"},"Vulshok Berserker":{"cmc":4,"colors":"R","rarity":"C"},"Bloodfire Kavu":{"cmc":4,"colors":"R","rarity":"U"},"Stone Giant":{"cmc":4,"colors":"R","rarity":"U"},"Geyser Glider":{"cmc":5,"colors":"R","rarity":"U"},"Lithophage":{"cmc":5,"colors":"R","rarity":"R"},"Torchling":{"cmc":5,"colors":"R","rarity":"R"},"Chartooth Cougar":{"cmc":6,"colors":"R","rarity":"C"},"Earth Servant":{"cmc":6,"colors":"R","rarity":"U"},"Greater Stone Spirit":{"cmc":6,"colors":"R","rarity":"U"},"Bloodfire Colossus":{"cmc":8,"colors":"R","rarity":"R"},"Wayfarer's Bauble":{"cmc":1,"colors":"C","rarity":"C"},"Armillary Sphere":{"cmc":2,"colors":"C","rarity":"C"},"Journeyer's Kite":{"cmc":2,"colors":"C","rarity":"R"},"Vulshok Morningstar":{"cmc":2,"colors":"C","rarity":"U"},"Searing Blaze":{"cmc":2,"colors":"R","rarity":"C"},"Vulshok Battlegear":{"cmc":3,"colors":"C","rarity":"U"},"Downhill Charge":{"cmc":3,"colors":"R","rarity":"C"},"Seismic Strike":{"cmc":3,"colors":"R","rarity":"C"},"Spire Barrage":{"cmc":5,"colors":"R","rarity":"C"},"Jaws of Stone":{"cmc":6,"colors":"R","rarity":"U"},"Volley of Boulders":{"cmc":9,"colors":"R","rarity":"R"},"Mountain":{"cmc":0,"colors":"R","rarity":"B"}}