{"Boomerang":{"cmc":2,"colors":"U","rarity":"r","type":"O"},"Calciderm":{"cmc":4,"colors":"W","rarity":"r","type":"C"},"Dauntless Dourbark":{"cmc":4,"colors":"G","rarity":"r","type":"C"},"Llanowar Elves":{"cmc":1,"colors":"G","rarity":"r","type":"C"},"Mind Stone":{"cmc":2,"colors":"","rarity":"r","type":"O"},"Mogg Fanatic":{"cmc":1,"colors":"R","rarity":"r","type":"C"},"Reckless Wurm":{"cmc":5,"colors":"R","rarity":"r","type":"C"},"Yixlid Jailer":{"cmc":2,"colors":"B","rarity":"r","type":"C"},"Zoetic Cavern":{"cmc":0,"colors":"C","rarity":"r","type":"L"}}