{"Abyssal Nightstalker":{"cmc":4,"colors":"B","rarity":"U","type":"C"},"Air Elemental":{"cmc":5,"colors":"U","rarity":"U","type":"C"},"Alaborn Cavalier":{"cmc":4,"colors":"W","rarity":"U","type":"C"},"Alaborn Grenadier":{"cmc":2,"colors":"W","rarity":"C","type":"C"},"Alaborn Musketeer":{"cmc":2,"colors":"W","rarity":"C","type":"C"},"Alaborn Trooper":{"cmc":3,"colors":"W","rarity":"C","type":"C"},"Alaborn Veteran":{"cmc":3,"colors":"W","rarity":"R","type":"C"},"Alaborn Zealot":{"cmc":1,"colors":"W","rarity":"U","type":"C"},"Alluring Scent":{"cmc":3,"colors":"G","rarity":"R","type":"O"},"Ancient Craving":{"cmc":4,"colors":"B","rarity":"R","type":"O"},"Angel of Fury":{"cmc":6,"colors":"W","rarity":"R","type":"C"},"Angel of Mercy":{"cmc":5,"colors":"W","rarity":"U","type":"C"},"Angelic Blessing":{"cmc":3,"colors":"W","rarity":"C","type":"O"},"Angelic Wall":{"cmc":2,"colors":"W","rarity":"C","type":"C"},"Apprentice Sorcerer":{"cmc":3,"colors":"U","rarity":"U","type":"C"},"Archangel":{"cmc":7,"colors":"W","rarity":"R","type":"C"},"Armageddon":{"cmc":4,"colors":"W","rarity":"R","type":"O"},"Armored Galleon":{"cmc":5,"colors":"U","rarity":"U","type":"C"},"Armored Griffin":{"cmc":4,"colors":"W","rarity":"U","type":"C"},"Barbtooth Wurm":{"cmc":6,"colors":"G","rarity":"C","type":"C"},"Bargain":{"cmc":3,"colors":"W","rarity":"U","type":"O"},"Bear Cub":{"cmc":2,"colors":"G","rarity":"C","type":"C"},"Bee Sting":{"cmc":4,"colors":"G","rarity":"U","type":"O"},"Blaze":{"cmc":1,"colors":"R","rarity":"U","type":"O"},"Bloodcurdling Scream":{"cmc":1,"colors":"B","rarity":"U","type":"O"},"Breath of Life":{"cmc":4,"colors":"W","rarity":"C","type":"O"},"Brimstone Dragon":{"cmc":8,"colors":"R","rarity":"R","type":"C"},"Brutal Nightstalker":{"cmc":5,"colors":"B","rarity":"U","type":"C"},"Chorus of Woe":{"cmc":1,"colors":"B","rarity":"C","type":"O"},"Coastal Wizard":{"cmc":4,"colors":"U","rarity":"R","type":"C"},"Coercion":{"cmc":3,"colors":"B","rarity":"U","type":"O"},"Cruel Edict":{"cmc":2,"colors":"B","rarity":"C","type":"O"},"Cunning Giant":{"cmc":6,"colors":"R","rarity":"R","type":"C"},"Dakmor Bat":{"cmc":2,"colors":"B","rarity":"C","type":"C"},"Dakmor Plague":{"cmc":5,"colors":"B","rarity":"U","type":"O"},"Dakmor Scorpion":{"cmc":2,"colors":"B","rarity":"C","type":"C"},"Dakmor Sorceress":{"cmc":6,"colors":"B","rarity":"R","type":"C"},"Dark Offering":{"cmc":6,"colors":"B","rarity":"U","type":"O"},"Deathcoil Wurm":{"cmc":8,"colors":"G","rarity":"R","type":"C"},"Deep Wood":{"cmc":2,"colors":"G","rarity":"U","type":"O"},"Déjà Vu":{"cmc":3,"colors":"U","rarity":"C","type":"O"},"Denizen of the Deep":{"cmc":8,"colors":"U","rarity":"R","type":"C"},"Earthquake":{"cmc":1,"colors":"R","rarity":"R","type":"O"},"Exhaustion":{"cmc":3,"colors":"U","rarity":"R","type":"O"},"Extinguish":{"cmc":2,"colors":"U","rarity":"C","type":"O"},"Eye Spy":{"cmc":1,"colors":"U","rarity":"U","type":"O"},"False Summoning":{"cmc":2,"colors":"U","rarity":"C","type":"O"},"Festival of Trokin":{"cmc":1,"colors":"W","rarity":"C","type":"O"},"Forest":{"cmc":0,"colors":"C","rarity":"B","type":"L"},"Foul Spirit":{"cmc":3,"colors":"B","rarity":"U","type":"C"},"Goblin Cavaliers":{"cmc":3,"colors":"R","rarity":"C","type":"C"},"Goblin Firestarter":{"cmc":1,"colors":"R","rarity":"U","type":"C"},"Goblin General":{"cmc":3,"colors":"R","rarity":"R","type":"C"},"Goblin Glider":{"cmc":2,"colors":"R","rarity":"C","type":"C"},"Goblin Lore":{"cmc":2,"colors":"R","rarity":"U","type":"O"},"Goblin Matron":{"cmc":3,"colors":"R","rarity":"U","type":"C"},"Goblin Mountaineer":{"cmc":1,"colors":"R","rarity":"C","type":"C"},"Goblin Piker":{"cmc":2,"colors":"R","rarity":"C","type":"C"},"Goblin Raider":{"cmc":2,"colors":"R","rarity":"C","type":"C"},"Goblin War Cry":{"cmc":3,"colors":"R","rarity":"U","type":"O"},"Goblin War Strike":{"cmc":1,"colors":"R","rarity":"C","type":"O"},"Golden Bear":{"cmc":4,"colors":"G","rarity":"C","type":"C"},"Hand of Death":{"cmc":3,"colors":"B","rarity":"C","type":"O"},"Harmony of Nature":{"cmc":3,"colors":"G","rarity":"U","type":"O"},"Hidden Horror":{"cmc":3,"colors":"B","rarity":"R","type":"C"},"Hurricane":{"cmc":1,"colors":"G","rarity":"R","type":"O"},"Ironhoof Ox":{"cmc":5,"colors":"G","rarity":"U","type":"C"},"Island":{"cmc":0,"colors":"C","rarity":"B","type":"L"},"Jagged Lightning":{"cmc":5,"colors":"R","rarity":"U","type":"O"},"Just Fate":{"cmc":3,"colors":"W","rarity":"R","type":"O"},"Kiss of Death":{"cmc":6,"colors":"B","rarity":"U","type":"O"},"Lava Axe":{"cmc":5,"colors":"R","rarity":"C","type":"O"},"Lone Wolf":{"cmc":3,"colors":"G","rarity":"U","type":"C"},"Lurking Nightstalker":{"cmc":2,"colors":"B","rarity":"C","type":"C"},"Lynx":{"cmc":2,"colors":"G","rarity":"C","type":"C"},"Magma Giant":{"cmc":7,"colors":"R","rarity":"R","type":"C"},"Mind Rot":{"cmc":3,"colors":"B","rarity":"C","type":"O"},"Moaning Spirit":{"cmc":3,"colors":"B","rarity":"C","type":"C"},"Monstrous Growth":{"cmc":2,"colors":"G","rarity":"C","type":"O"},"Mountain":{"cmc":0,"colors":"C","rarity":"B","type":"L"},"Muck Rats":{"cmc":1,"colors":"B","rarity":"C","type":"C"},"Mystic Denial":{"cmc":3,"colors":"U","rarity":"U","type":"O"},"Natural Spring":{"cmc":5,"colors":"G","rarity":"C","type":"O"},"Nature's Lore":{"cmc":2,"colors":"G","rarity":"C","type":"O"},"Nightstalker Engine":{"cmc":5,"colors":"B","rarity":"R","type":"C"},"Norwood Archers":{"cmc":4,"colors":"G","rarity":"C","type":"C"},"Norwood Priestess":{"cmc":4,"colors":"G","rarity":"R","type":"C"},"Norwood Ranger":{"cmc":1,"colors":"G","rarity":"C","type":"C"},"Norwood Riders":{"cmc":4,"colors":"G","rarity":"C","type":"C"},"Norwood Warrior":{"cmc":3,"colors":"G","rarity":"C","type":"C"},"Obsidian Giant":{"cmc":5,"colors":"R","rarity":"U","type":"C"},"Ogre Arsonist":{"cmc":5,"colors":"R","rarity":"U","type":"C"},"Ogre Berserker":{"cmc":5,"colors":"R","rarity":"C","type":"C"},"Ogre Taskmaster":{"cmc":4,"colors":"R","rarity":"U","type":"C"},"Ogre Warrior":{"cmc":4,"colors":"R","rarity":"C","type":"C"},"Path of Peace":{"cmc":4,"colors":"W","rarity":"C","type":"O"},"Piracy":{"cmc":2,"colors":"U","rarity":"R","type":"O"},"Plains":{"cmc":0,"colors":"C","rarity":"B","type":"L"},"Plated Wurm":{"cmc":5,"colors":"G","rarity":"C","type":"C"},"Predatory Nightstalker":{"cmc":5,"colors":"B","rarity":"U","type":"C"},"Prowling Nightstalker":{"cmc":4,"colors":"B","rarity":"C","type":"C"},"Raging Goblin":{"cmc":1,"colors":"R","rarity":"C","type":"C"},"Raiding Nightstalker":{"cmc":3,"colors":"B","rarity":"C","type":"C"},"Rain of Daggers":{"cmc":6,"colors":"B","rarity":"R","type":"O"},"Raise Dead":{"cmc":1,"colors":"B","rarity":"C","type":"O"},"Rally the Troops":{"cmc":1,"colors":"W","rarity":"U","type":"O"},"Ravenous Rats":{"cmc":2,"colors":"B","rarity":"C","type":"C"},"Razorclaw Bear":{"cmc":4,"colors":"G","rarity":"R","type":"C"},"Relentless Assault":{"cmc":4,"colors":"R","rarity":"R","type":"O"},"Remove":{"cmc":1,"colors":"U","rarity":"U","type":"O"},"Renewing Touch":{"cmc":1,"colors":"G","rarity":"U","type":"O"},"Return of the Nightstalkers":{"cmc":7,"colors":"B","rarity":"R","type":"O"},"Righteous Charge":{"cmc":3,"colors":"W","rarity":"C","type":"O"},"Righteous Fury":{"cmc":6,"colors":"W","rarity":"R","type":"O"},"River Bear":{"cmc":4,"colors":"G","rarity":"U","type":"C"},"Salvage":{"cmc":1,"colors":"G","rarity":"C","type":"O"},"Screeching Drake":{"cmc":4,"colors":"U","rarity":"C","type":"C"},"Sea Drake":{"cmc":3,"colors":"U","rarity":"U","type":"C"},"Sleight of Hand":{"cmc":1,"colors":"U","rarity":"C","type":"O"},"Spitting Earth":{"cmc":2,"colors":"R","rarity":"C","type":"O"},"Steam Catapult":{"cmc":5,"colors":"W","rarity":"R","type":"C"},"Steam Frigate":{"cmc":3,"colors":"U","rarity":"C","type":"C"},"Stone Rain":{"cmc":3,"colors":"R","rarity":"C","type":"O"},"Swamp":{"cmc":0,"colors":"C","rarity":"B","type":"L"},"Swarm of Rats":{"cmc":2,"colors":"B","rarity":"C","type":"C"},"Sylvan Basilisk":{"cmc":5,"colors":"G","rarity":"R","type":"C"},"Sylvan Yeti":{"cmc":4,"colors":"G","rarity":"R","type":"C"},"Talas Air Ship":{"cmc":4,"colors":"U","rarity":"C","type":"C"},"Talas Explorer":{"cmc":2,"colors":"U","rarity":"C","type":"C"},"Talas Merchant":{"cmc":2,"colors":"U","rarity":"C","type":"C"},"Talas Researcher":{"cmc":5,"colors":"U","rarity":"R","type":"C"},"Talas Scout":{"cmc":2,"colors":"U","rarity":"C","type":"C"},"Talas Warrior":{"cmc":3,"colors":"U","rarity":"R","type":"C"},"Temple Acolyte":{"cmc":2,"colors":"W","rarity":"C","type":"C"},"Temple Elder":{"cmc":3,"colors":"W","rarity":"U","type":"C"},"Temporal Manipulation":{"cmc":5,"colors":"U","rarity":"R","type":"O"},"Theft of Dreams":{"cmc":3,"colors":"U","rarity":"U","type":"O"},"Tidal Surge":{"cmc":2,"colors":"U","rarity":"C","type":"O"},"Time Ebb":{"cmc":3,"colors":"U","rarity":"C","type":"O"},"Touch of Brilliance":{"cmc":4,"colors":"U","rarity":"C","type":"O"},"Town Sentry":{"cmc":3,"colors":"W","rarity":"C","type":"C"},"Tree Monkey":{"cmc":1,"colors":"G","rarity":"C","type":"C"},"Tremor":{"cmc":1,"colors":"R","rarity":"C","type":"O"},"Trokin High Guard":{"cmc":4,"colors":"W","rarity":"C","type":"C"},"Undo":{"cmc":3,"colors":"U","rarity":"U","type":"O"},"Untamed Wilds":{"cmc":3,"colors":"G","rarity":"U","type":"O"},"Vampiric Spirit":{"cmc":4,"colors":"B","rarity":"R","type":"C"},"Vengeance":{"cmc":4,"colors":"W","rarity":"U","type":"O"},"Volcanic Hammer":{"cmc":2,"colors":"R","rarity":"C","type":"O"},"Volunteer Militia":{"cmc":1,"colors":"W","rarity":"C","type":"C"},"Warrior's Stand":{"cmc":2,"colors":"W","rarity":"U","type":"O"},"Wild Griffin":{"cmc":3,"colors":"W","rarity":"C","type":"C"},"Wild Ox":{"cmc":4,"colors":"G","rarity":"U","type":"C"},"Wildfire":{"cmc":6,"colors":"R","rarity":"R","type":"O"},"Wind Sail":{"cmc":2,"colors":"U","rarity":"C","type":"O"}}